{
  "name": "Verna Lewis",
  "age": 46,
  "address": {
    "street": "Zidrav Avenue",
    "city": "Pichorvo",
    "state": "NH",
    "zip": "23881"
  },
  "contact": {
    "phone": "(336) 896-9907",
    "servicePhone": "800967426"
  },
  "birthday": "2001-07-19T04:56:53.659Z",
  "ip": "198.125.89.57",
  "foo": "bar",
  "profile": {
    "about": "Jipohov boh honaece luesma ukakeifa albaho mivot rip um opsik danijko ka witotdiw. Duskomot kogkak atvivon uhanec vav lemo iztazhi elo hukru waevosa zeg bitmi ocgihok vojdih pebhesleb neipu evilimu. Wa bi mebtokik lo rasha deumojil fasokham pob boritof buhozas idovuh komtaldo pezofabaw ke.",
    "bio": "Janfoop berni ham tarvezec igraz cafek dakul lap kukom lin lajure giujome vejvoben keklal. Natno kohiwzo reduege jufgi bopot op sejaj kaz kerva ize vonah rocuvuh cij buper puwana gigejesi sa subbismik. Uz ukoledku kudwov agre gak hikjo venetzo nuzcaz upieheceh uvobza jiw mafvoluh jeatru ondu odu lifce pisfaf wa. Ewbav otecuw zuloh losdis verkuz dogu re dudmudpi kaurli uco paduz josarik ka hu wo subipo nacajwem mi."
  },
  "apiKey": "9f5837ef35a11947587c2fcbc85b93e4360fd7e8e1841dd52baec7a9522546b1",
  "currency": {
    "code": "UAH",
    "name": "Ukraine Hryvnia"
  }
}