{
  "name": "Allen Floyd",
  "age": 62,
  "address": {
    "street": "Fose Manor",
    "city": "Hupbufjo",
    "state": "OK",
    "zip": "44224"
  },
  "contact": {
    "phone": "(266) 204-3582",
    "servicePhone": "800472374"
  },
  "birthday": "1985-04-02T05:51:21.852Z",
  "ip": "184.238.45.17",
  "foo": "bar",
  "profile": {
    "about": "Kabjab nuzkebzu rav upe pi nubisnoz lehuw kakbe wumkaj obujeuw ge pa. Ewe fo dot ka tac povdok ignad jo nutlased wudzojha hatulfa najto vewajci objikak mu. Wud wubwaoj afo du liwa inreh kahoslu ti enabar ba oloob lo we sew du epinadubo buggufeg owatenza. Didsag ja lajonre cubjelav caw epeciwe elrogpi rekibvi hejer wehof nagfodhun parpoh unu. Liefino wi mom edded neze fi cehakni vuno zil fot nunoeh led mafoci van.",
    "bio": "Enper adehuz hizi hapu eso nilwagdik fas nu onakocle unfos cu umbohlew zeh jatzu umjupru wugje siwaru rokuda. Wepudov bebipe jobizog ri mi sogiz imnad kal uho acusoek ezbifi da fer mi apjacon te genne. Cin fim couc umwuh hi rud mirozzap adigof gakriag cinoni jurlafeha wusbe jelsica zaguv."
  },
  "apiKey": "089c135e3d07800b80d5b5b8d95236c572a5214bab33379f81e1aa7a65c41d2a",
  "currency": {
    "code": "GYD",
    "name": "Guyana Dollar"
  }
}