{
  "name": "Alvin Hale",
  "age": 43,
  "address": {
    "street": "Muwo Heights",
    "city": "Linsugoh",
    "state": "MA",
    "zip": "34171"
  },
  "contact": {
    "phone": "(387) 964-6254",
    "servicePhone": "800115254"
  },
  "birthday": "1963-11-06T18:12:51.804Z",
  "ip": "157.199.43.10",
  "foo": "bar",
  "profile": {
    "about": "Urobicid onne idda fahiw ke cib ef fejebigi hotam sujva lusentiv su aplu zushicnu mavoicu. Akhu je laow vu jah kuagbug ta mumwomew efutetowu cec rivfoh wiptabol vot puna mofwoj. Rid niwaku ro tucmag osetaz datpinma fase timtemroc awozabnu belkewato ve zeh towbawer rarral kiolwi cugvunru patutpa. Rajukwaw uwo ecce dut fage toce dadus banwanap panosse sarlebkok zungu dowsandu hoj cuzdimi bi lahifato cif. Ebkez mo co bipolji polutaf fijehvuk gol zatutuke socutfo ijuso je filorbic somod ihotsa sopcillup tirfe.",
    "bio": "Liravi hiewcol tinaul do pikva opebe milda kusasbok bapget pu iz bahgobbah vid oja woddaj. Mepus anihu dot zefcarpac bakogo workopda bik lakah wa si bisesa wi mu gofrumeru si paz pezafopu wud. Aj pozmumsi jum akirowi iposojit miw pulma rirzocna amo ivso mevili zaemjus ramilu zod fetja ni roju. Sagpe popadebuz de sogva gicget vabimfo nibohulo zajur dupi so du tadije ne ri kegnu ruobaca mim. Rojudi pa uf fasepluc gedej nicpo huse muk von rap icairdi ramherjo ohhez ec op jaedidi. Jo gebatab vodduvhiw jivis tubuwooce olefahwol lemwurur niegfu sepez kabcopi vo oceapni edoinsog fiw min ebojulul imuwze."
  },
  "apiKey": "c46a823a4f1c049c464036621782ade86562e691a74f26a19632e344fc986d1e",
  "currency": {
    "code": "KWD",
    "name": "Kuwait Dinar"
  }
}