{
  "name": "Barry McCarthy",
  "age": 26,
  "address": {
    "street": "Puis River",
    "city": "Sizupcel",
    "state": "NV",
    "zip": "28259"
  },
  "contact": {
    "phone": "(518) 550-8169",
    "servicePhone": "800472861"
  },
  "birthday": "1984-07-12T22:32:16.578Z",
  "ip": "198.25.197.127",
  "foo": "bar",
  "profile": {
    "about": "Uvsibuc samoc mov fiuj sagop pivjotod zas hag ropasso mamuffac desjovit ko. Ce koh pu ahluczaf tucu emag bat vof wuv hacnit mu re ehe uwewihgew gutgi dumfem wo. Pebzopufo cikvesdab igvug etfelina mu hi tewepip pir mumomgok vuka vow cujeleco. Em cit pap bok guudunuf odu ofsus pu ko wilsemco zutev ih amdaffun avu bek cepuco najhin diopiped. Secre ere famibwus latmaw zogi zokdaazo tiginu camvaume amu son caljur no mek voz.",
    "bio": "Noic hatampu jag uf kizomoke suwevni zu lel pociti niblem bim giotavu. Nukep eceev muc ubti wof bew daaza rongiov iveduji vocahfig romad epe okefowof algim ohdufeb duodamov. Gernuje be med dit ifubij vu jo zafejgu kut dosap rudap henaf ufounewud gofi zacajcar cehwok jiura."
  },
  "apiKey": "f23a88688a580597c6216fdc29695488d5a1de8c4990dda9498ba3844df29c1f",
  "currency": {
    "code": "HNL",
    "name": "Honduras Lempira"
  }
}